nornir_netbox/__init__.py
nornir_netbox/plugins/__init__.py
nornir_netbox/plugins/inventory/__init__.py
nornir_netbox/plugins/inventory/netbox.py
nornir_netbox-0.2.1.dist-info/entry_points.txt
nornir_netbox-0.2.1.dist-info/LICENSE
nornir_netbox-0.2.1.dist-info/WHEEL
nornir_netbox-0.2.1.dist-info/METADATA
nornir_netbox-0.2.1.dist-info/RECORD
