Metadata-Version: 2.1
Name: nornir-netbox
Version: 0.2.1
Summary: Netbox plugin for Nornir
License: Apache-2.0
Author: Wim Van Deun
Author-email: 7521270+enzzzy@users.noreply.github.com
Requires-Python: >=3.6,<4.0
Classifier: License :: OSI Approved :: Apache Software License
Classifier: Programming Language :: Python :: 3
Classifier: Programming Language :: Python :: 3.6
Classifier: Programming Language :: Python :: 3.7
Classifier: Programming Language :: Python :: 3.8
Classifier: Programming Language :: Python :: 3.9
Requires-Dist: nornir (>=3,<4)
Requires-Dist: requests (>=2.23.0,<3.0.0)
